CPLS/BaseDFSM.py
CPLS/DFSM.py
CPLS/FSM.py
CPLS/__init__.py
CPLS/base_classes.py
CPLS/master.py
CPLS/menu.py
CPLS/base_configs/__init__.py
CPLS/base_configs/cgc_config.json
CPLS/base_configs/file_observer_config.json
CPLS/base_configs/init_config.json
CPLS/base_configs/logger_config.json
CPLS/base_configs/paths_config.json
CPLS/base_configs/project_config.json
CPLS/services/__init__.py
CPLS/services/Conf_manager_service/__init__.py
CPLS/services/Conf_manager_service/configs_manager.py
CPLS/services/Creator_service/__init__.py
CPLS/services/Creator_service/creator.py
CPLS/services/Custom_garbage_collector_service/__init__.py
CPLS/services/Custom_garbage_collector_service/cgc.py
CPLS/services/File_observer_service/__init__.py
CPLS/services/File_observer_service/file_observer.py
CPLS/services/Json_h/__init__.py
CPLS/services/Json_h/json_h.py
CPLS/services/Logger_service/__init__.py
CPLS/services/Logger_service/base_saver.py
CPLS/services/Logger_service/csv_log_saver.py
CPLS/services/Logger_service/json_log_saver.py
CPLS/services/Logger_service/logger.py
CPLS/services/Logger_service/txt_log_saver.py
CPLS/services/Path_service/__init__.py
CPLS/services/Path_service/base_path_obj.py
CPLS/services/Path_service/category.py
CPLS/services/Path_service/datatype_file.py
CPLS/services/Path_service/path_index.py
CPLS-0.0.1.dist-info/LICENSE
CPLS-0.0.1.dist-info/METADATA
CPLS-0.0.1.dist-info/WHEEL
CPLS-0.0.1.dist-info/top_level.txt
CPLS-0.0.1.dist-info/RECORD
