Metadata-Version: 2.1
Name: CPLS
Version: 0.0.1
Summary: Centralized Project Launch System
Home-page: https://github.com/Manul147/General-Arcgitecture
Author: Максуров Денис
Author-email: denismaksyrov@bk.ru
Classifier: Programming Language :: Python :: 3
Classifier: License :: OSI Approved :: Apache Software License
Classifier: Operating System :: OS Independent
Requires-Python: >=3.9
License-File: LICENSE
Requires-Dist: annotated-types==0.7.0
Requires-Dist: fix-busted-json==0.0.18
Requires-Dist: pydantic==2.10.3
Requires-Dist: pydantic_core==2.27.1
Requires-Dist: typing_extensions==4.12.2
Requires-Dist: watchdog==6.0.0
